[
  {
    "text": "Library / penf.F90",
    "collapsed": true,
    "items": [
      {
        "text": "penf",
        "link": "/api/penf"
      }
    ]
  },
  {
    "text": "Library / penf_allocatable_memory.F90",
    "collapsed": true,
    "items": [
      {
        "text": "penf_allocatable_memory",
        "link": "/api/penf_allocatable_memory"
      }
    ]
  },
  {
    "text": "Library / penf_b_size.F90",
    "collapsed": true,
    "items": [
      {
        "text": "penf_b_size",
        "link": "/api/penf_b_size"
      }
    ]
  },
  {
    "text": "Library / penf_global_parameters_variables.F90",
    "collapsed": true,
    "items": [
      {
        "text": "penf_global_parameters_variables",
        "link": "/api/penf_global_parameters_variables"
      }
    ]
  },
  {
    "text": "Library / penf_stringify.F90",
    "collapsed": true,
    "items": [
      {
        "text": "penf_stringify",
        "link": "/api/penf_stringify"
      }
    ]
  }
]